TradingView/__init__.py
TradingView/chart_session.py
TradingView/client.py
TradingView/protocol.py
TradingView/search.py
TradingView/types.py
TradingView/utils.py
tradingview_api-1.0.1.dist-info/licenses/LICENSE
tradingview_api-1.0.1.dist-info/METADATA
tradingview_api-1.0.1.dist-info/WHEEL
tradingview_api-1.0.1.dist-info/top_level.txt
tradingview_api-1.0.1.dist-info/RECORD
