Metadata-Version: 2.4
Name: TradingView-API
Version: 1.0.1
Summary: Python implementation for anonymous access to TradingView market data via WebSocket and symbol search
Home-page: https://github.com/kaash04/TradingView-API-Python
Author: TradingView Python API Contributors
Author-email: 
License: MIT
Project-URL: Homepage, https://github.com/kaash04/TradingView-API-Python
Project-URL: Repository, https://github.com/kaash04/TradingView-API-Python
Project-URL: Documentation, https://github.com/kaash04/TradingView-API-Python#readme
Project-URL: Bug Tracker, https://github.com/kaash04/TradingView-API-Python/issues
Keywords: tradingview,websocket,api,financial,trading,market-data
Classifier: Development Status :: 4 - Beta
Classifier: Intended Audience :: Developers
Classifier: License :: OSI Approved :: MIT License
Classifier: Operating System :: OS Independent
Classifier: Programming Language :: Python :: 3
Classifier: Programming Language :: Python :: 3.7
Classifier: Programming Language :: Python :: 3.8
Classifier: Programming Language :: Python :: 3.9
Classifier: Programming Language :: Python :: 3.10
Classifier: Programming Language :: Python :: 3.11
Classifier: Topic :: Office/Business :: Financial :: Investment
Classifier: Topic :: Software Development :: Libraries :: Python Modules
Requires-Python: >=3.7
License-File: LICENSE
Requires-Dist: websockets>=10.0
Requires-Dist: requests>=2.25.0
Provides-Extra: dev
Requires-Dist: pytest>=6.0; extra == "dev"
Requires-Dist: pytest-asyncio>=0.18.0; extra == "dev"
Requires-Dist: black>=21.0; extra == "dev"
Requires-Dist: flake8>=3.8; extra == "dev"
Requires-Dist: mypy>=0.800; extra == "dev"
Dynamic: home-page
Dynamic: license-file
Dynamic: requires-python
